{
    "_links": {
        "self": "http://husky.lo:7878/admin/api/columnnavigation/0",
        "children": "http://husky.lo:7878/admin/api/columnnavigation/children?parent=0&depth=1"
    },
    "_embedded": [
        {
            "title": "Page 1 has a way too long title",
            "id": "1",
            "hasSub": true,
            "publishedState": true,
            "linked": "internal",
            "type": {
                "name": "false",
                "value": "false"
            },
            "_links": {
                "self": "http://husky.lo:7878/admin/api/columnnavigation/1",
                "children": "http://husky.lo:7878/admin/api/columnnavigation/children?parent=1&depth=1"
            },
            "_embedded": []
        },
        {
            "title": "Page 2",
            "id": "2",
            "hasSub": true,
            "publishedState": true,
            "linked": "external",
            "type": {
                "name": "false",
                "value": "false"
            },
            "_links": {
                "self": "http://husky.lo:7878/admin/api/columnnavigation/2",
                "children": "http://husky.lo:7878/admin/api/columnnavigation/children?parent=2&depth=1"
            },
            "_embedded": []
        },
        {
            "title": "Page 3",
            "id": "3",
            "hasSub": false,
            "publishedState": false,
            "linked": false,
            "type": {
                "name": "ghost",
                "value": "us_en"
            },
            "_links": {
                "self": "http://husky.lo:7878/admin/api/columnnavigation/3",
                "children": "http://husky.lo:7878/admin/api/columnnavigation/children?parent=3&depth=1"
            },
            "_embedded": []
        },
        {
            "title": "Page 4",
            "id": "4",
            "hasSub": false,
            "publishedState": true,
            "linked": false,
            "type": {
                "name": "shadow",
                "value": "true"
            },
            "_links": {
                "self": "http://husky.lo:7878/admin/api/columnnavigation/4",
                "children": "http://husky.lo:7878/admin/api/columnnavigation/children?parent=4&depth=1"
            },
            "_embedded": []
        },
        {
            "title": "Page 5",
            "id": "5",
            "hasSub": false,
            "publishedState": false,
            "linked": "internal",
            "type": {
                "name": "ghost",
                "value": "us_en"
            },
            "_links": {
                "self": "http://husky.lo:7878/admin/api/columnnavigation/5",
                "children": "http://husky.lo:7878/admin/api/columnnavigation/children?parent=5&depth=1"
            },
            "_embedded": []
        },
        {
            "title": "Page 6",
            "id": "6",
            "hasSub": false,
            "publishedState": true,
            "linked": "external",
            "type": {
                "name": "shadow",
                "value": true
            },
            "_links": {
                "self": "http://husky.lo:7878/admin/api/columnnavigation/6",
                "children": "http://husky.lo:7878/admin/api/columnnavigation/children?parent=6&depth=1"
            },
            "_embedded": []
        },
        {
            "title": "Page 7",
            "id": "7",
            "hasSub": false,
            "publishedState": false,
            "linked": false,
            "type": false,
            "_links": {
                "self": "http://husky.lo:7878/admin/api/columnnavigation/7",
                "children": "http://husky.lo:7878/admin/api/columnnavigation/children?parent=7&depth=1"
            },
            "_embedded": []
        },
        {
            "title": "Page 8",
            "id": "8",
            "hasSub": true,
            "publishedState": false,
            "linked": false,
            "type": false,
            "_links": {
                "self": "http://husky.lo:7878/admin/api/columnnavigation/8",
                "children": "http://husky.lo:7878/admin/api/columnnavigation/children?parent=8&depth=1"
            },
            "_embedded": []
        },
        {
            "title": "Page 9",
            "id": "9",
            "hasSub": false,
            "publishedState": false,
            "linked": false,
            "type": false,
            "_links": {
                "self": "http://husky.lo:7878/admin/api/columnnavigation/9",
                "children": "http://husky.lo:7878/admin/api/columnnavigation/children?parent=9&depth=1"
            },
            "_embedded": []
        }
    ],
    "title": "Root",
    "id": "0",
    "hasSub": true
}
